atcoder_doctest/__init__.py
atcoder_doctest/atcoder_doctest.py
atcoder_doctest-0.0.1.dist-info/METADATA
atcoder_doctest-0.0.1.dist-info/WHEEL
atcoder_doctest-0.0.1.dist-info/entry_points.txt
atcoder_doctest-0.0.1.dist-info/top_level.txt
atcoder_doctest-0.0.1.dist-info/RECORD
