Metadata-Version: 2.1
Name: atcoder-doctest
Version: 0.0.1
Summary: Generate texts from AtCoder problem page.
Home-page: https://github.com/muro3r/AtCoder-doctest/
Author: UNKNOWN
Author-email: UNKNOWN
License: UNKNOWN
Platform: UNKNOWN
Requires-Dist: beautifulsoup4
Requires-Dist: requests
